aerospace_chatbot/.DS_Store
aerospace_chatbot/__init__.py
aerospace_chatbot/core/__init__.py
aerospace_chatbot/core/config.py
aerospace_chatbot/processing/__init__.py
aerospace_chatbot/processing/documents.py
aerospace_chatbot/processing/queries.py
aerospace_chatbot/services/__init__.py
aerospace_chatbot/services/database.py
aerospace_chatbot/services/embeddings.py
aerospace_chatbot/services/llm.py
aerospace_chatbot/services/prompts.py
aerospace_chatbot/ui/__init__.py
aerospace_chatbot/ui/admin.py
aerospace_chatbot/ui/utils.py
aerospace_chatbot-0.0.10.1.dist-info/LICENSE
aerospace_chatbot-0.0.10.1.dist-info/METADATA
aerospace_chatbot-0.0.10.1.dist-info/WHEEL
aerospace_chatbot-0.0.10.1.dist-info/RECORD
